{"inkVersion":20,"root":[[["done",{"#f":5,"#n":"g-0"}],null],"done",{"gameEvent":[{"temp=":"eventName"},"ev","void","/ev","~ret",{"#f":1}],"returnStringEvent":[{"temp=":"eventName"},"ev","str","^emptyString","/str","/ev","~ret",{"#f":1}],"teleport":[["ev","str","^getTeleportText","/str",{"x()":"returnStringEvent","exArgs":1},"pop","/ev","\n","ev","str","^Yes","/str","/ev",{"*":".^.c-0","flg":4},"ev","str","^No","/str","/ev",{"*":".^.c-1","flg":4},{"c-0":["^ ",{"->":".^.^.^.enter"},"\n",{"#f":5}],"c-1":["^ ",{"->":".^.^.^.cancel"},"\n",{"#f":5}]}],{"enter":["ev","str","^teleport","/str",{"x()":"gameEvent","exArgs":1},"pop","/ev","\n",{"->":".^.^.end"},{"#f":1}],"cancel":["^You decide against it.","\n",{"->":".^.^.end"},{"#f":1}],"end":["end",{"#f":1}],"#f":1}],"global decl":["ev","str","^emptyString","/str",{"VAR=":"teleportString"},"/ev","end",null],"#f":1}],"listDefs":{}}